pyboot/__init__.py
pyboot/cli.py
pyboot/pyboot.py
pyboot/template/MANIFEST.in
pyboot/template/README.md
pyboot/template/setup.cfg
pyboot/template/setup.py-tpl
pyboot/template/package_name/__init__.py-tpl
pyboot/template/package_name/cli.py-tpl
pyboot/template/package_name/package_name.py-tpl
pyboot/template/package_name/text.md
pyboot/template/tests/__init__.py-tpl
pyboot/template/tests/test_command.py-tpl
tests/__init__.py
tests/test_command.py
pyboot-0.3.0.dist-info/METADATA
pyboot-0.3.0.dist-info/WHEEL
pyboot-0.3.0.dist-info/entry_points.txt
pyboot-0.3.0.dist-info/top_level.txt
pyboot-0.3.0.dist-info/RECORD
