Metadata-Version: 2.1
Name: pyboot
Version: 0.3.0
Summary: A python project bootstraper
Home-page: https://gitlab.com/plup/pyboot
Author: Plup
Author-email: plup@plup.io
License: ISC
Platform: UNKNOWN
Classifier: Programming Language :: Python :: 3
Classifier: Operating System :: OS Independent
Requires-Python: >=3.8
Requires-Dist: click
Requires-Dist: Jinja2
Provides-Extra: dev
Requires-Dist: tox ; extra == 'dev'
